[{
        "href": "https://www.auto-data.net/bg/bmw-02-e10-model-943",
        "model": "02 (E10)"
    },
    {
        "href": "https://www.auto-data.net/bg/bmw-1-series-model-948",
        "model": "Серия 1"
    },
    {
        "href": "https://www.auto-data.net/bg/bmw-2-series-model-2027",
        "model": "Серия 2"
    },
    {
        "href": "https://www.auto-data.net/bg/bmw-3-series-model-953",
        "model": "Серия 3"
    },
    {
        "href": "https://www.auto-data.net/bg/bmw-4-series-model-2011",
        "model": "Серия 4"
    },
    {
        "href": "https://www.auto-data.net/bg/bmw-5-series-model-944",
        "model": "Серия 5"
    },
    {
        "href": "https://www.auto-data.net/bg/bmw-6-series-model-949",
        "model": "Серия 6"
    },
    {
        "href": "https://www.auto-data.net/bg/bmw-7-series-model-945",
        "model": "Серия 7"
    },
    {
        "href": "https://www.auto-data.net/bg/bmw-700-model-2878",
        "model": "700"
    },
    {
        "href": "https://www.auto-data.net/bg/bmw-8-series-model-950",
        "model": "Серия 8"
    },
    {
        "href": "https://www.auto-data.net/bg/bmw-e9-model-2954",
        "model": "E9"
    },
    {
        "href": "https://www.auto-data.net/bg/bmw-i3-model-2034",
        "model": "i3"
    },
    {
        "href": "https://www.auto-data.net/bg/bmw-i4-model-2925",
        "model": "i4"
    },
    {
        "href": "https://www.auto-data.net/bg/bmw-i7-model-3105",
        "model": "i7"
    },
    {
        "href": "https://www.auto-data.net/bg/bmw-i8-model-2035",
        "model": "i8"
    },
    {
        "href": "https://www.auto-data.net/bg/bmw-isetta-model-3015",
        "model": "Isetta"
    },
    {
        "href": "https://www.auto-data.net/bg/bmw-ix-model-2924",
        "model": "iX"
    },
    {
        "href": "https://www.auto-data.net/bg/bmw-ix3-model-2822",
        "model": "iX3"
    },
    {
        "href": "https://www.auto-data.net/bg/bmw-ix5-model-2990",
        "model": "iX5"
    },
    {
        "href": "https://www.auto-data.net/bg/bmw-m1-model-2979",
        "model": "M1"
    },
    {
        "href": "https://www.auto-data.net/bg/bmw-m2-model-2093",
        "model": "M2"
    },
    {
        "href": "https://www.auto-data.net/bg/bmw-m3-model-1986",
        "model": "M3"
    },
    {
        "href": "https://www.auto-data.net/bg/bmw-m4-model-2039",
        "model": "M4"
    },
    {
        "href": "https://www.auto-data.net/bg/bmw-m5-model-1987",
        "model": "M5"
    },
    {
        "href": "https://www.auto-data.net/bg/bmw-m6-model-951",
        "model": "M6"
    },
    {
        "href": "https://www.auto-data.net/bg/bmw-m8-model-2343",
        "model": "M8"
    },
    {
        "href": "https://www.auto-data.net/bg/bmw-new-class-model-2961",
        "model": "New Class"
    },
    {
        "href": "https://www.auto-data.net/bg/bmw-x1-model-1983",
        "model": "X1"
    },
    {
        "href": "https://www.auto-data.net/bg/bmw-x2-model-2316",
        "model": "X2"
    },
    {
        "href": "https://www.auto-data.net/bg/bmw-x3-model-1984",
        "model": "X3"
    },
    {
        "href": "https://www.auto-data.net/bg/bmw-x3-m-model-2625",
        "model": "X3 M"
    },
    {
        "href": "https://www.auto-data.net/bg/bmw-x4-model-2040",
        "model": "X4"
    },
    {
        "href": "https://www.auto-data.net/bg/bmw-x4-m-model-2624",
        "model": "X4 M"
    },
    {
        "href": "https://www.auto-data.net/bg/bmw-x5-model-1985",
        "model": "X5"
    },
    {
        "href": "https://www.auto-data.net/bg/bmw-x5-m-model-2480",
        "model": "X5 M"
    },
    {
        "href": "https://www.auto-data.net/bg/bmw-x6-model-947",
        "model": "X6"
    },
    {
        "href": "https://www.auto-data.net/bg/bmw-x6-m-model-2481",
        "model": "X6 M"
    },
    {
        "href": "https://www.auto-data.net/bg/bmw-x7-model-2344",
        "model": "X7"
    },
    {
        "href": "https://www.auto-data.net/bg/bmw-z1-model-1990",
        "model": "Z1"
    },
    {
        "href": "https://www.auto-data.net/bg/bmw-z3-model-1991",
        "model": "Z3"
    },
    {
        "href": "https://www.auto-data.net/bg/bmw-z4-model-1992",
        "model": "Z4"
    },
    {
        "href": "https://www.auto-data.net/bg/bmw-z8-model-952",
        "model": "Z8"
    }
]